addon_utils/__init__.pyi
addon_utils/py.typed
animsys_refactor/__init__.pyi
animsys_refactor/py.typed
aud/__init__.pyi
aud/py.typed
bgl/__init__.pyi
bgl/py.typed
bl_app_override/__init__.pyi
bl_app_override/py.typed
bl_app_override/helpers/__init__.pyi
bl_app_template_utils/__init__.pyi
bl_app_template_utils/py.typed
bl_console_utils/__init__.pyi
bl_console_utils/py.typed
bl_console_utils/autocomplete/__init__.pyi
bl_console_utils/autocomplete/complete_calltip/__init__.pyi
bl_console_utils/autocomplete/complete_import/__init__.pyi
bl_console_utils/autocomplete/complete_namespace/__init__.pyi
bl_console_utils/autocomplete/intellisense/__init__.pyi
bl_i18n_utils/__init__.pyi
bl_i18n_utils/py.typed
bl_i18n_utils/bl_extract_messages/__init__.pyi
bl_i18n_utils/merge_po/__init__.pyi
bl_i18n_utils/settings/__init__.pyi
bl_i18n_utils/utils/__init__.pyi
bl_i18n_utils/utils_cli/__init__.pyi
bl_i18n_utils/utils_languages_menu/__init__.pyi
bl_i18n_utils/utils_rtl/__init__.pyi
bl_keymap_utils/__init__.pyi
bl_keymap_utils/py.typed
bl_keymap_utils/io/__init__.pyi
bl_keymap_utils/keymap_from_toolbar/__init__.pyi
bl_keymap_utils/keymap_hierarchy/__init__.pyi
bl_keymap_utils/platform_helpers/__init__.pyi
bl_keymap_utils/versioning/__init__.pyi
bl_math/__init__.pyi
bl_math/py.typed
bl_operators/__init__.pyi
bl_operators/py.typed
bl_operators/add_mesh_torus/__init__.pyi
bl_operators/anim/__init__.pyi
bl_operators/assets/__init__.pyi
bl_operators/bmesh/__init__.pyi
bl_operators/bmesh/find_adjacent/__init__.pyi
bl_operators/clip/__init__.pyi
bl_operators/console/__init__.pyi
bl_operators/constraint/__init__.pyi
bl_operators/file/__init__.pyi
bl_operators/freestyle/__init__.pyi
bl_operators/geometry_nodes/__init__.pyi
bl_operators/image/__init__.pyi
bl_operators/mesh/__init__.pyi
bl_operators/node/__init__.pyi
bl_operators/object/__init__.pyi
bl_operators/object_align/__init__.pyi
bl_operators/object_quick_effects/__init__.pyi
bl_operators/object_randomize_transform/__init__.pyi
fake_bpy_module_4.0-20250130.dist-info/METADATA
fake_bpy_module_4.0-20250130.dist-info/WHEEL
fake_bpy_module_4.0-20250130.dist-info/top_level.txt
fake_bpy_module_4.0-20250130.dist-info/RECORD
